{
  "project_info": {
    "project_number": "308239218493",
    "project_id": "gpio-control"
  },
  "client": [
    {
      "client_info": {
        "mobilesdk_app_id": "1:308239218493:android:195ac01fb96e9c74",
        "android_client_info": {
          "package_name": "org.kaaproject.kaa.examples.gpiocontrol"
        }
      },
      "oauth_client": [
        {
          "client_id": "308239218493-5t7ge9bgfrq6e46j4jmdtahkkjp5orck.apps.googleusercontent.com",
          "client_type": 3
        },
        {
          "client_id": "308239218493-cf35fgnva3j2ohv1m5hvf4b3p404na50.apps.googleusercontent.com",
          "client_type": 1,
          "android_info": {
            "package_name": "org.kaaproject.kaa.examples.gpiocontrol",
            "certificate_hash": "1759e1a94647cb46499fa308e5849c13886f315c"
          }
        }
      ],
      "api_key": [
        {
          "current_key": "AIzaSyAO23TkYEzB1osGvpQxsItKFtWerr0flnE"
        }
      ],
      "services": {
        "analytics_service": {
          "status": 1
        },
        "appinvite_service": {
          "status": 1,
          "other_platform_oauth_client": []
        },
        "ads_service": {
          "status": 1
        }
      }
    }
  ],
  "configuration_version": "1"
}